__init__.py
test-packaging-rss/RSSreader.py
test-packaging-rss/__init__.py
test-packaging-rss/example.py
test_rss_pkg/RSSreader.py
test_rss_pkg/__init__.py
test_rss_pkg/example.py
test_packaging_rss-0.0.7.dist-info/LICENSE
test_packaging_rss-0.0.7.dist-info/METADATA
test_packaging_rss-0.0.7.dist-info/WHEEL
test_packaging_rss-0.0.7.dist-info/top_level.txt
test_packaging_rss-0.0.7.dist-info/RECORD
