Metadata-Version: 2.1
Name: test-packaging-rss
Version: 0.0.7
Summary: test packaging
Home-page: https://github.com/baobabtr33/test-packaging-rss
Author: Kim Jung Hwan
Author-email: author@example.com
License: UNKNOWN
Platform: UNKNOWN
Requires-Dist: feedparser
